CHANGELOG.rst
LICENSE
MANIFEST.in
Makefile
README.rst
docs-requirements.txt
molotov.json
requirements.txt
setup.py
tox-requirements.txt
tox.ini
molotov/__init__.py
molotov/api.py
molotov/demo.py
molotov/dummy.py
molotov/listeners.py
molotov/run.py
molotov/runner.py
molotov/session.py
molotov/slave.py
molotov/stats.py
molotov/util.py
molotov/worker.py
molotov.egg-info/PKG-INFO
molotov.egg-info/SOURCES.txt
molotov.egg-info/dependency_links.txt
molotov.egg-info/entry_points.txt
molotov.egg-info/not-zip-safe
molotov.egg-info/requires.txt
molotov.egg-info/top_level.txt
molotov/quickstart/Makefile
molotov/quickstart/__init__.py
molotov/quickstart/loadtest.py
molotov/quickstart/molotov.json
molotov/shared/__init__.py
molotov/shared/counter.py
molotov/shared/tasks.py
molotov/tests/__init__.py
molotov/tests/conftest.py
molotov/tests/example.py
molotov/tests/example2.py
molotov/tests/example3.py
molotov/tests/example4.py
molotov/tests/example5.py
molotov/tests/example6.py
molotov/tests/example7.py
molotov/tests/example8.py
molotov/tests/example9.py
molotov/tests/molotov.json
molotov/tests/mylib.py
molotov/tests/statsd.py
molotov/tests/support.py
molotov/tests/test_api.py
molotov/tests/test_fmwk.py
molotov/tests/test_listeners.py
molotov/tests/test_quickstart.py
molotov/tests/test_run.py
molotov/tests/test_session.py
molotov/tests/test_sharedconsole.py
molotov/tests/test_sharedcounter.py
molotov/tests/test_slave.py
molotov/tests/test_util.py
molotov/ui/__init__.py
molotov/ui/app.py
molotov/ui/console.py
molotov/ui/controllers.py