Metadata-Version: 2.1
Name: molotov
Version: 2.6
Summary: Spiffy load testing tool.
Home-page: https://molotov.readthedocs.io
Author: Tarek Ziade
Author-email: tarek@ziade.org
Classifier: Programming Language :: Python
Classifier: License :: OSI Approved :: Apache Software License
Classifier: Development Status :: 5 - Production/Stable
Classifier: Programming Language :: Python :: 3 :: Only
Classifier: Programming Language :: Python :: 3.7
Classifier: Programming Language :: Python :: 3.8
Classifier: Programming Language :: Python :: 3.9
Classifier: Programming Language :: Python :: 3.10
License-File: LICENSE
